appium_extended/__init__.py
appium_extended/appium_base.py
appium_extended/appium_extended.py
appium_extended/appium_get.py
appium_extended/appium_is.py
appium_extended/appium_swipe.py
appium_extended/appium_tap.py
appium_extended/appium_wait.py
appium_extended_graph/__init__.py
appium_extended_graph/appium_graph.py
appium_extended_helpers/__init__.py
appium_extended_helpers/appium_helpers.py
appium_extended_helpers/appium_image.py
appium_extended_helpers/helpers_decorators.py
appium_extended_navigator/__init__.py
appium_extended_navigator/appium_navigator.py
appium_extended_server/__init__.py
appium_extended_server/appium_server.py
appium_extended_terminal/__init__.py
appium_extended_terminal/aapt.py
appium_extended_terminal/adb.py
appium_extended_terminal/terminal.py
appium_extended_utils/__init__.py
appium_extended_utils/operations.py
appium_extended_utils/utils.py
appium_extended_web_element/__init__.py
appium_extended_web_element/web_element_adb_actions.py
appium_extended_web_element/web_element_click.py
appium_extended_web_element/web_element_dom.py
appium_extended_web_element/web_element_extended.py
appium_extended_web_element/web_element_get.py
appium_extended_web_element/web_element_scroll.py
appium_extended_web_element/web_element_tap.py
AppiumExtended-0.1.33.dist-info/LICENSE
AppiumExtended-0.1.33.dist-info/METADATA
AppiumExtended-0.1.33.dist-info/WHEEL
AppiumExtended-0.1.33.dist-info/top_level.txt
AppiumExtended-0.1.33.dist-info/RECORD
